<?xml version='1.0' encoding='UTF-8'?>
<document>
  <supplier>Lumber Inc</supplier>
  <invoice_number>FA04/2021/081651</invoice_number>
  <po_number>BC06591</po_number>
  <invoice_date>20210414</invoice_date>
  <invoice_date_due>20210713</invoice_date_due>
  <address>1337 N San Joaquin St  Stockton CA 95202 États Unis</address>
  <total_untaxed>828045.5</total_untaxed>
  <tax_amount>163261.95</tax_amount>
  <total_amount>163261.95</total_amount>
  <lines>
    <line>
      <description>Tiroir</description>
      <quantity>56.0</quantity>
      <uom>Unités</uom>
      <price>100.0</price>
      <tax></tax>
      <sub_total>5600.0</sub_total>
    </line>
    <line>
      <description>Grande table de réunion</description>
      <quantity>78.0</quantity>
      <uom>Unités</uom>
      <price>4500.0</price>
      <tax>TVA 20%</tax>
      <sub_total>351000.0</sub_total>
    </line>
    <line>
      <description>Restaurant</description>
      <quantity>99.0</quantity>
      <uom>Unités</uom>
      <price>8.0</price>
      <tax>TVA 20%</tax>
      <sub_total>792.0</sub_total>
    </line>
    <line>
      <description>Bureau personnalisable</description>
      <quantity>9.0</quantity>
      <uom>Unités</uom>
      <price>500.0</price>
      <tax>TVA 20%</tax>
      <sub_total>4500.0</sub_total>
    </line>
    <line>
      <description>Poubelle à pédale</description>
      <quantity>46.0</quantity>
      <uom>Unités</uom>
      <price>10.0</price>
      <tax>TVA 20%</tax>
      <sub_total>460.0</sub_total>
    </line>
    <line>
      <description>Armoire avec portes</description>
      <quantity>63.0</quantity>
      <uom>Unités</uom>
      <price>120.5</price>
      <tax>TVA 10%</tax>
      <sub_total>7591.5</sub_total>
    </line>
    <line>
      <description>Chaise de bureau noire</description>
      <quantity>26.0</quantity>
      <uom>Unités</uom>
      <price>180.0</price>
      <tax>TVA 10%</tax>
      <sub_total>4680.0</sub_total>
    </line>
    <line>
      <description>Grande armoire</description>
      <quantity>34.0</quantity>
      <uom>Unités</uom>
      <price>800.0</price>
      <tax>TVA 20%</tax>
      <sub_total>27200.0</sub_total>
    </line>
    <line>
      <description>Bureau d'angle avec siège à gauche</description>
      <quantity>99.0</quantity>
      <uom>Unités</uom>
      <price>78.0</price>
      <tax>TVA 20%</tax>
      <sub_total>7722.0</sub_total>
    </line>
    <line>
      <description>Grande table de réunion</description>
      <quantity>93.0</quantity>
      <uom>Unités</uom>
      <price>4500.0</price>
      <tax>TVA 20%</tax>
      <sub_total>418500.0</sub_total>
    </line>
  </lines>
</document>
