<?xml version='1.0' encoding='UTF-8'?>
<document>
  <supplier>Gemini Furniture</supplier>
  <invoice_number>FA01/2019/065448</invoice_number>
  <po_number>BC09286</po_number>
  <invoice_date>20190101</invoice_date>
  <invoice_date_due>20190116</invoice_date_due>
  <address>317 Fairchild Dr  Fairfield CA 94535 États Unis</address>
  <total_untaxed>24255.0</total_untaxed>
  <tax_amount>1185.5</tax_amount>
  <total_amount>1185.5</total_amount>
  <lines>
    <line>
      <description>Poubelle à pédale</description>
      <quantity>29.0</quantity>
      <uom>Unités</uom>
      <price>10.0</price>
      <tax>TVA 20%</tax>
      <sub_total>290.0</sub_total>
    </line>
    <line>
      <description>Support de bureau avec écran</description>
      <quantity>8.0</quantity>
      <uom>Unités</uom>
      <price>2010.0</price>
      <tax></tax>
      <sub_total>16080.0</sub_total>
    </line>
    <line>
      <description>Chaise de bureau</description>
      <quantity>87.0</quantity>
      <uom>Unités</uom>
      <price>55.0</price>
      <tax>TVA 20%</tax>
      <sub_total>4785.0</sub_total>
    </line>
    <line>
      <description>Dépôt</description>
      <quantity>31.0</quantity>
      <uom>Unités</uom>
      <price>100.0</price>
      <tax>TVA 5,5%</tax>
      <sub_total>3100.0</sub_total>
    </line>
  </lines>
</document>
