<?xml version='1.0' encoding='UTF-8'?>
<document>
  <supplier>Azure Interior</supplier>
  <invoice_number>FA04/2015/085324</invoice_number>
  <po_number>BC06159</po_number>
  <invoice_date>2015-04-12</invoice_date>
  <invoice_date_due>2015-05-27</invoice_date_due>
  <currency_id>EUR</currency_id>
  <address>4557 De Silva St  Fremont CA 94538 États Unis</address>
  <total_untaxed>78070.0</total_untaxed>
  <tax_amount>13634.0</tax_amount>
  <total_amount>13634.0</total_amount>
  <lines>
    <line>
      <description>Bureau personnalisable</description>
      <quantity>31.0</quantity>
      <uom>Unités</uom>
      <price>500.0</price>
      <tax>TVA 20%</tax>
      <sub_total>15500.0</sub_total>
    </line>
    <line>
      <description>Combinaison de bureau</description>
      <quantity>66.0</quantity>
      <uom>Unités</uom>
      <price>300.0</price>
      <tax>TVA 10%</tax>
      <sub_total>19800.0</sub_total>
    </line>
    <line>
      <description>Canapé trois places</description>
      <quantity>42.0</quantity>
      <uom>Unités</uom>
      <price>1000.0</price>
      <tax>TVA 20%</tax>
      <sub_total>42000.0</sub_total>
    </line>
    <line>
      <description>Poubelle à pédale</description>
      <quantity>77.0</quantity>
      <uom>Unités</uom>
      <price>10.0</price>
      <tax>TVA 20%</tax>
      <sub_total>770.0</sub_total>
    </line>
  </lines>
</document>
