<?xml version='1.0' encoding='UTF-8'?>
<document>
  <supplier>The Jackson Group</supplier>
  <invoice_number>FA01/2019/008385</invoice_number>
  <po_number>BC08041</po_number>
  <invoice_date>2019-01-22</invoice_date>
  <invoice_date_due>2019-03-08</invoice_date_due>
  <currency_id>EUR</currency_id>
  <address>1611 Peony Dr  Tracy CA 95377 États Unis</address>
  <total_untaxed>153490.0</total_untaxed>
  <tax_amount>28930.0</tax_amount>
  <total_amount>28930.0</total_amount>
  <lines>
    <line>
      <description>Tiroir</description>
      <quantity>31.0</quantity>
      <uom>Unités</uom>
      <price>100.0</price>
      <tax></tax>
      <sub_total>3100.0</sub_total>
    </line>
    <line>
      <description>Canapé trois places</description>
      <quantity>12.0</quantity>
      <uom>Unités</uom>
      <price>1000.0</price>
      <tax>TVA 20%</tax>
      <sub_total>12000.0</sub_total>
    </line>
    <line>
      <description>Architecte Junior (Facturation sur Feuilles de Temps)</description>
      <quantity>70.0</quantity>
      <uom>Heures</uom>
      <price>85.0</price>
      <tax>TVA 20%</tax>
      <sub_total>5950.0</sub_total>
    </line>
    <line>
      <description>Grande table de réunion</description>
      <quantity>26.0</quantity>
      <uom>Unités</uom>
      <price>4500.0</price>
      <tax>TVA 20%</tax>
      <sub_total>117000.0</sub_total>
    </line>
    <line>
      <description>Architecte Principal (Facturation sur Feuilles de Temps)</description>
      <quantity>61.0</quantity>
      <uom>Heures</uom>
      <price>150.0</price>
      <tax>TVA 20%</tax>
      <sub_total>9150.0</sub_total>
    </line>
    <line>
      <description>Écrans ant-bruit</description>
      <quantity>20.0</quantity>
      <uom>Unités</uom>
      <price>287.0</price>
      <tax></tax>
      <sub_total>5740.0</sub_total>
    </line>
    <line>
      <description>Poubelle à pédale</description>
      <quantity>55.0</quantity>
      <uom>Unités</uom>
      <price>10.0</price>
      <tax>TVA 20%</tax>
      <sub_total>550.0</sub_total>
    </line>
  </lines>
</document>
