<?xml version='1.0' encoding='UTF-8'?>
<document>
  <supplier>Wood Corner</supplier>
  <invoice_number>FA01/2019/005421</invoice_number>
  <po_number>BC03950</po_number>
  <invoice_date>2019-01-04</invoice_date>
  <invoice_date_due>2019-02-03</invoice_date_due>
  <currency_id>EUR</currency_id>
  <address>1839 Arbor Way  Turlock CA 95380 États Unis</address>
  <total_untaxed>100576.0</total_untaxed>
  <tax_amount>15962.66</tax_amount>
  <total_amount>15962.66</total_amount>
  <lines>
    <line>
      <description>Bureau personnalisable</description>
      <quantity>6.0</quantity>
      <uom>Unités</uom>
      <price>500.0</price>
      <tax>TVA 20%</tax>
      <sub_total>3000.0</sub_total>
    </line>
    <line>
      <description>Bureau personnalisable</description>
      <quantity>85.0</quantity>
      <uom>Unités</uom>
      <price>500.0</price>
      <tax>TVA 20%</tax>
      <sub_total>42500.0</sub_total>
    </line>
    <line>
      <description>Tiroir</description>
      <quantity>84.0</quantity>
      <uom>Unités</uom>
      <price>100.0</price>
      <tax></tax>
      <sub_total>8400.0</sub_total>
    </line>
    <line>
      <description>Grande armoire</description>
      <quantity>27.0</quantity>
      <uom>Unités</uom>
      <price>800.0</price>
      <tax>TVA 20%</tax>
      <sub_total>21600.0</sub_total>
    </line>
    <line>
      <description>Bureau personnalisable</description>
      <quantity>5.0</quantity>
      <uom>Unités</uom>
      <price>500.0</price>
      <tax>TVA 20%</tax>
      <sub_total>2500.0</sub_total>
    </line>
    <line>
      <description>Service Client (Heures Prépayées)</description>
      <quantity>29.0</quantity>
      <uom>Heures</uom>
      <price>190.0</price>
      <tax>TVA 20%</tax>
      <sub_total>5510.0</sub_total>
    </line>
    <line>
      <description>Flipover</description>
      <quantity>9.0</quantity>
      <uom>Unités</uom>
      <price>1700.0</price>
      <tax>TVA 5,5%</tax>
      <sub_total>15300.0</sub_total>
    </line>
    <line>
      <description>Espace de travail individuel</description>
      <quantity>2.0</quantity>
      <uom>Unités</uom>
      <price>876.0</price>
      <tax>TVA 5,5%</tax>
      <sub_total>1752.0</sub_total>
    </line>
    <line>
      <description>Boîte de rangement</description>
      <quantity>1.0</quantity>
      <uom>Unités</uom>
      <price>14.0</price>
      <tax>TVA 20%</tax>
      <sub_total>14.0</sub_total>
    </line>
  </lines>
</document>
