<?xml version='1.0' encoding='UTF-8'?>
<document>
  <supplier>Gemini Furniture</supplier>
  <invoice_number>FA07/2018/084994</invoice_number>
  <po_number>BC00059</po_number>
  <invoice_date>2018-07-10</invoice_date>
  <invoice_date_due>2018-07-10</invoice_date_due>
  <currency_id>EUR</currency_id>
  <address>317 Fairchild Dr  Fairfield CA 94535 États Unis</address>
  <total_untaxed>646288.0</total_untaxed>
  <tax_amount>123827.58</tax_amount>
  <total_amount>123827.58</total_amount>
  <lines>
    <line>
      <description>Hôtel</description>
      <quantity>26.0</quantity>
      <uom>Jours</uom>
      <price>400.0</price>
      <tax>TVA 20%</tax>
      <sub_total>10400.0</sub_total>
    </line>
    <line>
      <description>Service Client (Heures Prépayées)</description>
      <quantity>33.0</quantity>
      <uom>Heures</uom>
      <price>190.0</price>
      <tax>TVA 20%</tax>
      <sub_total>6270.0</sub_total>
    </line>
    <line>
      <description>Écrans ant-bruit</description>
      <quantity>4.0</quantity>
      <uom>Unités</uom>
      <price>287.0</price>
      <tax></tax>
      <sub_total>1148.0</sub_total>
    </line>
    <line>
      <description>Espace de travail individuel</description>
      <quantity>31.0</quantity>
      <uom>Unités</uom>
      <price>876.0</price>
      <tax>TVA 5,5%</tax>
      <sub_total>27156.0</sub_total>
    </line>
    <line>
      <description>Écrans ant-bruit</description>
      <quantity>22.0</quantity>
      <uom>Unités</uom>
      <price>287.0</price>
      <tax></tax>
      <sub_total>6314.0</sub_total>
    </line>
    <line>
      <description>Grande table de réunion</description>
      <quantity>99.0</quantity>
      <uom>Unités</uom>
      <price>4500.0</price>
      <tax>TVA 20%</tax>
      <sub_total>445500.0</sub_total>
    </line>
    <line>
      <description>Grande table de réunion</description>
      <quantity>25.0</quantity>
      <uom>Unités</uom>
      <price>4500.0</price>
      <tax>TVA 20%</tax>
      <sub_total>112500.0</sub_total>
    </line>
    <line>
      <description>Bureau personnalisable</description>
      <quantity>74.0</quantity>
      <uom>Unités</uom>
      <price>500.0</price>
      <tax>TVA 20%</tax>
      <sub_total>37000.0</sub_total>
    </line>
  </lines>
</document>
